devml
