Metadata-Version: 1.1
Name: devml
Version: 0.5.1
Summary: Machine Learning, Statistics and Utilities around Developer Productivity, 
Home-page: https://github.com/noahgift/devml
Author: Noah Gift
Author-email: consulting@noahgift.com
License: MIT
Platform: any
Classifier: Development Status :: 4 - Beta
Classifier: Intended Audience :: Developers
Classifier: License :: OSI Approved :: MIT License
Classifier: Programming Language :: Python
Classifier: Programming Language :: Python :: 3.6
Classifier: Topic :: Software Development :: Libraries :: Python Modules
